{
   "2018-04-21_21:42:24.501661_Y24TS9_N": {
      "neighbors": {},
      "event_id": {},
      "cumulative_intake_sum_since_reset": 0,
      "cumulative_fire_count": 0,
      "cumulative_fire_count_inst": 0,
      "cumulative_intake_total": 0,
      "cumulative_intake_count": 0,
      "consecutive_fire_cnt": 0,
      "snooze_till_burst_num": 0,
      "last_burst_num": 0,
      "location": [
         129,
         51,
         678
      ],
      "block": [
         13,
         6,
         68
      ],
      "status": "Passive",
      "last_timer_reset_time": "2018-04-21 21:42:24.501689",
      "firing_pattern_id": "",
      "activation_function_id": "",
      "timer_threshold": 50,
      "firing_threshold": 1
   },
   "2018-04-21_21:42:24.501697_S29V8H_N": {
      "neighbors": {},
      "event_id": {},
      "cumulative_intake_sum_since_reset": 0,
      "cumulative_fire_count": 0,
      "cumulative_fire_count_inst": 0,
      "cumulative_intake_total": 0,
      "cumulative_intake_count": 0,
      "consecutive_fire_cnt": 0,
      "snooze_till_burst_num": 0,
      "last_burst_num": 0,
      "location": [
         193,
         719,
         164
      ],
      "block": [
         20,
         72,
         17
      ],
      "status": "Passive",
      "last_timer_reset_time": "2018-04-21 21:42:24.501719",
      "firing_pattern_id": "",
      "activation_function_id": "",
      "timer_threshold": 50,
      "firing_threshold": 1
   },
   "2018-04-21_21:42:24.501726_TS2G0L_N": {
      "neighbors": {},
      "event_id": {},
      "cumulative_intake_sum_since_reset": 0,
      "cumulative_fire_count": 0,
      "cumulative_fire_count_inst": 0,
      "cumulative_intake_total": 0,
      "cumulative_intake_count": 0,
      "consecutive_fire_cnt": 0,
      "snooze_till_burst_num": 0,
      "last_burst_num": 0,
      "location": [
         567,
         137,
         285
      ],
      "block": [
         57,
         14,
         29
      ],
      "status": "Passive",
      "last_timer_reset_time": "2018-04-21 21:42:24.501756",
      "firing_pattern_id": "",
      "activation_function_id": "",
      "timer_threshold": 50,
      "firing_threshold": 1
   },
   "2018-04-21_21:42:24.501765_ANHG1N_N": {
      "neighbors": {},
      "event_id": {},
      "cumulative_intake_sum_since_reset": 0,
      "cumulative_fire_count": 0,
      "cumulative_fire_count_inst": 0,
      "cumulative_intake_total": 0,
      "cumulative_intake_count": 0,
      "consecutive_fire_cnt": 0,
      "snooze_till_burst_num": 0,
      "last_burst_num": 0,
      "location": [
         145,
         523,
         669
      ],
      "block": [
         15,
         53,
         67
      ],
      "status": "Passive",
      "last_timer_reset_time": "2018-04-21 21:42:24.501790",
      "firing_pattern_id": "",
      "activation_function_id": "",
      "timer_threshold": 50,
      "firing_threshold": 1
   },
   "2018-04-21_21:42:24.501797_IRP430_N": {
      "neighbors": {},
      "event_id": {},
      "cumulative_intake_sum_since_reset": 0,
      "cumulative_fire_count": 0,
      "cumulative_fire_count_inst": 0,
      "cumulative_intake_total": 0,
      "cumulative_intake_count": 0,
      "consecutive_fire_cnt": 0,
      "snooze_till_burst_num": 0,
      "last_burst_num": 0,
      "location": [
         606,
         796,
         339
      ],
      "block": [
         61,
         80,
         34
      ],
      "status": "Passive",
      "last_timer_reset_time": "2018-04-21 21:42:24.501819",
      "firing_pattern_id": "",
      "activation_function_id": "",
      "timer_threshold": 50,
      "firing_threshold": 1
   },
   "2018-04-21_21:42:24.501826_AJPCPS_N": {
      "neighbors": {},
      "event_id": {},
      "cumulative_intake_sum_since_reset": 0,
      "cumulative_fire_count": 0,
      "cumulative_fire_count_inst": 0,
      "cumulative_intake_total": 0,
      "cumulative_intake_count": 0,
      "consecutive_fire_cnt": 0,
      "snooze_till_burst_num": 0,
      "last_burst_num": 0,
      "location": [
         328,
         794,
         661
      ],
      "block": [
         33,
         80,
         67
      ],
      "status": "Passive",
      "last_timer_reset_time": "2018-04-21 21:42:24.501848",
      "firing_pattern_id": "",
      "activation_function_id": "",
      "timer_threshold": 50,
      "firing_threshold": 1
   },
   "2018-04-21_21:42:24.501855_R4PMZ5_N": {
      "neighbors": {},
      "event_id": {},
      "cumulative_intake_sum_since_reset": 0,
      "cumulative_fire_count": 0,
      "cumulative_fire_count_inst": 0,
      "cumulative_intake_total": 0,
      "cumulative_intake_count": 0,
      "consecutive_fire_cnt": 0,
      "snooze_till_burst_num": 0,
      "last_burst_num": 0,
      "location": [
         756,
         568,
         635
      ],
      "block": [
         76,
         57,
         64
      ],
      "status": "Passive",
      "last_timer_reset_time": "2018-04-21 21:42:24.501877",
      "firing_pattern_id": "",
      "activation_function_id": "",
      "timer_threshold": 50,
      "firing_threshold": 1
   },
   "2018-04-21_21:42:24.501884_4SV58B_N": {
      "neighbors": {},
      "event_id": {},
      "cumulative_intake_sum_since_reset": 0,
      "cumulative_fire_count": 0,
      "cumulative_fire_count_inst": 0,
      "cumulative_intake_total": 0,
      "cumulative_intake_count": 0,
      "consecutive_fire_cnt": 0,
      "snooze_till_burst_num": 0,
      "last_burst_num": 0,
      "location": [
         658,
         10,
         577
      ],
      "block": [
         66,
         1,
         58
      ],
      "status": "Passive",
      "last_timer_reset_time": "2018-04-21 21:42:24.501906",
      "firing_pattern_id": "",
      "activation_function_id": "",
      "timer_threshold": 50,
      "firing_threshold": 1
   },
   "2018-04-21_21:42:24.501913_I80VD4_N": {
      "neighbors": {},
      "event_id": {},
      "cumulative_intake_sum_since_reset": 0,
      "cumulative_fire_count": 0,
      "cumulative_fire_count_inst": 0,
      "cumulative_intake_total": 0,
      "cumulative_intake_count": 0,
      "consecutive_fire_cnt": 0,
      "snooze_till_burst_num": 0,
      "last_burst_num": 0,
      "location": [
         447,
         78,
         465
      ],
      "block": [
         45,
         8,
         47
      ],
      "status": "Passive",
      "last_timer_reset_time": "2018-04-21 21:42:24.501939",
      "firing_pattern_id": "",
      "activation_function_id": "",
      "timer_threshold": 50,
      "firing_threshold": 1
   },
   "2018-04-21_21:42:24.501947_M0USL2_N": {
      "neighbors": {},
      "event_id": {},
      "cumulative_intake_sum_since_reset": 0,
      "cumulative_fire_count": 0,
      "cumulative_fire_count_inst": 0,
      "cumulative_intake_total": 0,
      "cumulative_intake_count": 0,
      "consecutive_fire_cnt": 0,
      "snooze_till_burst_num": 0,
      "last_burst_num": 0,
      "location": [
         159,
         386,
         355
      ],
      "block": [
         16,
         39,
         36
      ],
      "status": "Passive",
      "last_timer_reset_time": "2018-04-21 21:42:24.501975",
      "firing_pattern_id": "",
      "activation_function_id": "",
      "timer_threshold": 50,
      "firing_threshold": 1
   },
   "2018-04-21_21:42:24.501984_0JDD5Y_N": {
      "neighbors": {},
      "event_id": {},
      "cumulative_intake_sum_since_reset": 0,
      "cumulative_fire_count": 0,
      "cumulative_fire_count_inst": 0,
      "cumulative_intake_total": 0,
      "cumulative_intake_count": 0,
      "consecutive_fire_cnt": 0,
      "snooze_till_burst_num": 0,
      "last_burst_num": 0,
      "location": [
         16,
         428,
         443
      ],
      "block": [
         2,
         43,
         45
      ],
      "status": "Passive",
      "last_timer_reset_time": "2018-04-21 21:42:24.502007",
      "firing_pattern_id": "",
      "activation_function_id": "",
      "timer_threshold": 50,
      "firing_threshold": 1
   },
   "2018-04-21_21:42:24.502014_KEQTVX_N": {
      "neighbors": {},
      "event_id": {},
      "cumulative_intake_sum_since_reset": 0,
      "cumulative_fire_count": 0,
      "cumulative_fire_count_inst": 0,
      "cumulative_intake_total": 0,
      "cumulative_intake_count": 0,
      "consecutive_fire_cnt": 0,
      "snooze_till_burst_num": 0,
      "last_burst_num": 0,
      "location": [
         531,
         509,
         322
      ],
      "block": [
         54,
         51,
         33
      ],
      "status": "Passive",
      "last_timer_reset_time": "2018-04-21 21:42:24.502037",
      "firing_pattern_id": "",
      "activation_function_id": "",
      "timer_threshold": 50,
      "firing_threshold": 1
   },
   "2018-04-21_21:42:24.502044_QLTSI6_N": {
      "neighbors": {},
      "event_id": {},
      "cumulative_intake_sum_since_reset": 0,
      "cumulative_fire_count": 0,
      "cumulative_fire_count_inst": 0,
      "cumulative_intake_total": 0,
      "cumulative_intake_count": 0,
      "consecutive_fire_cnt": 0,
      "snooze_till_burst_num": 0,
      "last_burst_num": 0,
      "location": [
         369,
         35,
         173
      ],
      "block": [
         37,
         4,
         18
      ],
      "status": "Passive",
      "last_timer_reset_time": "2018-04-21 21:42:24.502072",
      "firing_pattern_id": "",
      "activation_function_id": "",
      "timer_threshold": 50,
      "firing_threshold": 1
   },
   "2018-04-21_21:42:24.502081_XR0FMT_N": {
      "neighbors": {},
      "event_id": {},
      "cumulative_intake_sum_since_reset": 0,
      "cumulative_fire_count": 0,
      "cumulative_fire_count_inst": 0,
      "cumulative_intake_total": 0,
      "cumulative_intake_count": 0,
      "consecutive_fire_cnt": 0,
      "snooze_till_burst_num": 0,
      "last_burst_num": 0,
      "location": [
         193,
         937,
         260
      ],
      "block": [
         20,
         94,
         26
      ],
      "status": "Passive",
      "last_timer_reset_time": "2018-04-21 21:42:24.502103",
      "firing_pattern_id": "",
      "activation_function_id": "",
      "timer_threshold": 50,
      "firing_threshold": 1
   },
   "2018-04-21_21:42:24.502111_AA1XKI_N": {
      "neighbors": {},
      "event_id": {},
      "cumulative_intake_sum_since_reset": 0,
      "cumulative_fire_count": 0,
      "cumulative_fire_count_inst": 0,
      "cumulative_intake_total": 0,
      "cumulative_intake_count": 0,
      "consecutive_fire_cnt": 0,
      "snooze_till_burst_num": 0,
      "last_burst_num": 0,
      "location": [
         473,
         758,
         88
      ],
      "block": [
         48,
         76,
         9
      ],
      "status": "Passive",
      "last_timer_reset_time": "2018-04-21 21:42:24.502133",
      "firing_pattern_id": "",
      "activation_function_id": "",
      "timer_threshold": 50,
      "firing_threshold": 1
   },
   "2018-04-21_21:42:24.502140_R7O5WC_N": {
      "neighbors": {},
      "event_id": {},
      "cumulative_intake_sum_since_reset": 0,
      "cumulative_fire_count": 0,
      "cumulative_fire_count_inst": 0,
      "cumulative_intake_total": 0,
      "cumulative_intake_count": 0,
      "consecutive_fire_cnt": 0,
      "snooze_till_burst_num": 0,
      "last_burst_num": 0,
      "location": [
         966,
         423,
         279
      ],
      "block": [
         97,
         43,
         28
      ],
      "status": "Passive",
      "last_timer_reset_time": "2018-04-21 21:42:24.502168",
      "firing_pattern_id": "",
      "activation_function_id": "",
      "timer_threshold": 50,
      "firing_threshold": 1
   },
   "2018-04-21_21:42:24.502177_0SFR2V_N": {
      "neighbors": {},
      "event_id": {},
      "cumulative_intake_sum_since_reset": 0,
      "cumulative_fire_count": 0,
      "cumulative_fire_count_inst": 0,
      "cumulative_intake_total": 0,
      "cumulative_intake_count": 0,
      "consecutive_fire_cnt": 0,
      "snooze_till_burst_num": 0,
      "last_burst_num": 0,
      "location": [
         354,
         243,
         277
      ],
      "block": [
         36,
         25,
         28
      ],
      "status": "Passive",
      "last_timer_reset_time": "2018-04-21 21:42:24.502199",
      "firing_pattern_id": "",
      "activation_function_id": "",
      "timer_threshold": 50,
      "firing_threshold": 1
   },
   "2018-04-21_21:42:24.502207_03SR5E_N": {
      "neighbors": {},
      "event_id": {},
      "cumulative_intake_sum_since_reset": 0,
      "cumulative_fire_count": 0,
      "cumulative_fire_count_inst": 0,
      "cumulative_intake_total": 0,
      "cumulative_intake_count": 0,
      "consecutive_fire_cnt": 0,
      "snooze_till_burst_num": 0,
      "last_burst_num": 0,
      "location": [
         338,
         728,
         354
      ],
      "block": [
         34,
         73,
         36
      ],
      "status": "Passive",
      "last_timer_reset_time": "2018-04-21 21:42:24.502229",
      "firing_pattern_id": "",
      "activation_function_id": "",
      "timer_threshold": 50,
      "firing_threshold": 1
   },
   "2018-04-21_21:42:24.502236_8HSQI7_N": {
      "neighbors": {},
      "event_id": {},
      "cumulative_intake_sum_since_reset": 0,
      "cumulative_fire_count": 0,
      "cumulative_fire_count_inst": 0,
      "cumulative_intake_total": 0,
      "cumulative_intake_count": 0,
      "consecutive_fire_cnt": 0,
      "snooze_till_burst_num": 0,
      "last_burst_num": 0,
      "location": [
         962,
         506,
         343
      ],
      "block": [
         97,
         51,
         35
      ],
      "status": "Passive",
      "last_timer_reset_time": "2018-04-21 21:42:24.502258",
      "firing_pattern_id": "",
      "activation_function_id": "",
      "timer_threshold": 50,
      "firing_threshold": 1
   },
   "2018-04-21_21:42:24.502265_6DTV3O_N": {
      "neighbors": {},
      "event_id": {},
      "cumulative_intake_sum_since_reset": 0,
      "cumulative_fire_count": 0,
      "cumulative_fire_count_inst": 0,
      "cumulative_intake_total": 0,
      "cumulative_intake_count": 0,
      "consecutive_fire_cnt": 0,
      "snooze_till_burst_num": 0,
      "last_burst_num": 0,
      "location": [
         444,
         38,
         230
      ],
      "block": [
         45,
         4,
         23
      ],
      "status": "Passive",
      "last_timer_reset_time": "2018-04-21 21:42:24.502287",
      "firing_pattern_id": "",
      "activation_function_id": "",
      "timer_threshold": 50,
      "firing_threshold": 1
   },
   "2018-04-21_21:42:24.502295_J5E9H3_N": {
      "neighbors": {},
      "event_id": {},
      "cumulative_intake_sum_since_reset": 0,
      "cumulative_fire_count": 0,
      "cumulative_fire_count_inst": 0,
      "cumulative_intake_total": 0,
      "cumulative_intake_count": 0,
      "consecutive_fire_cnt": 0,
      "snooze_till_burst_num": 0,
      "last_burst_num": 0,
      "location": [
         827,
         748,
         698
      ],
      "block": [
         83,
         75,
         70
      ],
      "status": "Passive",
      "last_timer_reset_time": "2018-04-21 21:42:24.502332",
      "firing_pattern_id": "",
      "activation_function_id": "",
      "timer_threshold": 50,
      "firing_threshold": 1
   },
   "2018-04-21_21:42:24.502341_M9VGXP_N": {
      "neighbors": {},
      "event_id": {},
      "cumulative_intake_sum_since_reset": 0,
      "cumulative_fire_count": 0,
      "cumulative_fire_count_inst": 0,
      "cumulative_intake_total": 0,
      "cumulative_intake_count": 0,
      "consecutive_fire_cnt": 0,
      "snooze_till_burst_num": 0,
      "last_burst_num": 0,
      "location": [
         102,
         689,
         385
      ],
      "block": [
         11,
         69,
         39
      ],
      "status": "Passive",
      "last_timer_reset_time": "2018-04-21 21:42:24.502368",
      "firing_pattern_id": "",
      "activation_function_id": "",
      "timer_threshold": 50,
      "firing_threshold": 1
   },
   "2018-04-21_21:42:24.502376_GXM2GK_N": {
      "neighbors": {},
      "event_id": {},
      "cumulative_intake_sum_since_reset": 0,
      "cumulative_fire_count": 0,
      "cumulative_fire_count_inst": 0,
      "cumulative_intake_total": 0,
      "cumulative_intake_count": 0,
      "consecutive_fire_cnt": 0,
      "snooze_till_burst_num": 0,
      "last_burst_num": 0,
      "location": [
         657,
         206,
         695
      ],
      "block": [
         66,
         21,
         70
      ],
      "status": "Passive",
      "last_timer_reset_time": "2018-04-21 21:42:24.502399",
      "firing_pattern_id": "",
      "activation_function_id": "",
      "timer_threshold": 50,
      "firing_threshold": 1
   },
   "2018-04-21_21:42:24.502406_6QUUZT_N": {
      "neighbors": {},
      "event_id": {},
      "cumulative_intake_sum_since_reset": 0,
      "cumulative_fire_count": 0,
      "cumulative_fire_count_inst": 0,
      "cumulative_intake_total": 0,
      "cumulative_intake_count": 0,
      "consecutive_fire_cnt": 0,
      "snooze_till_burst_num": 0,
      "last_burst_num": 0,
      "location": [
         981,
         610,
         676
      ],
      "block": [
         99,
         61,
         68
      ],
      "status": "Passive",
      "last_timer_reset_time": "2018-04-21 21:42:24.502437",
      "firing_pattern_id": "",
      "activation_function_id": "",
      "timer_threshold": 50,
      "firing_threshold": 1
   },
   "2018-04-21_21:42:24.502444_YJIRWQ_N": {
      "neighbors": {},
      "event_id": {},
      "cumulative_intake_sum_since_reset": 0,
      "cumulative_fire_count": 0,
      "cumulative_fire_count_inst": 0,
      "cumulative_intake_total": 0,
      "cumulative_intake_count": 0,
      "consecutive_fire_cnt": 0,
      "snooze_till_burst_num": 0,
      "last_burst_num": 0,
      "location": [
         698,
         671,
         626
      ],
      "block": [
         70,
         68,
         63
      ],
      "status": "Passive",
      "last_timer_reset_time": "2018-04-21 21:42:24.502476",
      "firing_pattern_id": "",
      "activation_function_id": "",
      "timer_threshold": 50,
      "firing_threshold": 1
   },
   "2018-04-21_21:42:24.502485_G3QPGN_N": {
      "neighbors": {},
      "event_id": {},
      "cumulative_intake_sum_since_reset": 0,
      "cumulative_fire_count": 0,
      "cumulative_fire_count_inst": 0,
      "cumulative_intake_total": 0,
      "cumulative_intake_count": 0,
      "consecutive_fire_cnt": 0,
      "snooze_till_burst_num": 0,
      "last_burst_num": 0,
      "location": [
         266,
         382,
         499
      ],
      "block": [
         27,
         39,
         50
      ],
      "status": "Passive",
      "last_timer_reset_time": "2018-04-21 21:42:24.502511",
      "firing_pattern_id": "",
      "activation_function_id": "",
      "timer_threshold": 50,
      "firing_threshold": 1
   },
   "2018-04-21_21:42:24.502521_D1A7ZD_N": {
      "neighbors": {},
      "event_id": {},
      "cumulative_intake_sum_since_reset": 0,
      "cumulative_fire_count": 0,
      "cumulative_fire_count_inst": 0,
      "cumulative_intake_total": 0,
      "cumulative_intake_count": 0,
      "consecutive_fire_cnt": 0,
      "snooze_till_burst_num": 0,
      "last_burst_num": 0,
      "location": [
         903,
         801,
         684
      ],
      "block": [
         91,
         81,
         69
      ],
      "status": "Passive",
      "last_timer_reset_time": "2018-04-21 21:42:24.502543",
      "firing_pattern_id": "",
      "activation_function_id": "",
      "timer_threshold": 50,
      "firing_threshold": 1
   },
   "2018-04-21_21:42:24.502551_35Q243_N": {
      "neighbors": {},
      "event_id": {},
      "cumulative_intake_sum_since_reset": 0,
      "cumulative_fire_count": 0,
      "cumulative_fire_count_inst": 0,
      "cumulative_intake_total": 0,
      "cumulative_intake_count": 0,
      "consecutive_fire_cnt": 0,
      "snooze_till_burst_num": 0,
      "last_burst_num": 0,
      "location": [
         705,
         850,
         616
      ],
      "block": [
         71,
         85,
         62
      ],
      "status": "Passive",
      "last_timer_reset_time": "2018-04-21 21:42:24.502573",
      "firing_pattern_id": "",
      "activation_function_id": "",
      "timer_threshold": 50,
      "firing_threshold": 1
   },
   "2018-04-21_21:42:24.502580_ZHDYS7_N": {
      "neighbors": {},
      "event_id": {},
      "cumulative_intake_sum_since_reset": 0,
      "cumulative_fire_count": 0,
      "cumulative_fire_count_inst": 0,
      "cumulative_intake_total": 0,
      "cumulative_intake_count": 0,
      "consecutive_fire_cnt": 0,
      "snooze_till_burst_num": 0,
      "last_burst_num": 0,
      "location": [
         762,
         777,
         254
      ],
      "block": [
         77,
         78,
         26
      ],
      "status": "Passive",
      "last_timer_reset_time": "2018-04-21 21:42:24.502602",
      "firing_pattern_id": "",
      "activation_function_id": "",
      "timer_threshold": 50,
      "firing_threshold": 1
   },
   "2018-04-21_21:42:24.502609_HK3JDF_N": {
      "neighbors": {},
      "event_id": {},
      "cumulative_intake_sum_since_reset": 0,
      "cumulative_fire_count": 0,
      "cumulative_fire_count_inst": 0,
      "cumulative_intake_total": 0,
      "cumulative_intake_count": 0,
      "consecutive_fire_cnt": 0,
      "snooze_till_burst_num": 0,
      "last_burst_num": 0,
      "location": [
         186,
         838,
         665
      ],
      "block": [
         19,
         84,
         67
      ],
      "status": "Passive",
      "last_timer_reset_time": "2018-04-21 21:42:24.502631",
      "firing_pattern_id": "",
      "activation_function_id": "",
      "timer_threshold": 50,
      "firing_threshold": 1
   },
   "2018-04-21_21:42:24.502638_Z07VP8_N": {
      "neighbors": {},
      "event_id": {},
      "cumulative_intake_sum_since_reset": 0,
      "cumulative_fire_count": 0,
      "cumulative_fire_count_inst": 0,
      "cumulative_intake_total": 0,
      "cumulative_intake_count": 0,
      "consecutive_fire_cnt": 0,
      "snooze_till_burst_num": 0,
      "last_burst_num": 0,
      "location": [
         312,
         278,
         574
      ],
      "block": [
         32,
         28,
         58
      ],
      "status": "Passive",
      "last_timer_reset_time": "2018-04-21 21:42:24.502661",
      "firing_pattern_id": "",
      "activation_function_id": "",
      "timer_threshold": 50,
      "firing_threshold": 1
   },
   "2018-04-21_21:42:24.502668_SMHI3Y_N": {
      "neighbors": {},
      "event_id": {},
      "cumulative_intake_sum_since_reset": 0,
      "cumulative_fire_count": 0,
      "cumulative_fire_count_inst": 0,
      "cumulative_intake_total": 0,
      "cumulative_intake_count": 0,
      "consecutive_fire_cnt": 0,
      "snooze_till_burst_num": 0,
      "last_burst_num": 0,
      "location": [
         57,
         116,
         672
      ],
      "block": [
         6,
         12,
         68
      ],
      "status": "Passive",
      "last_timer_reset_time": "2018-04-21 21:42:24.502694",
      "firing_pattern_id": "",
      "activation_function_id": "",
      "timer_threshold": 50,
      "firing_threshold": 1
   },
   "2018-04-21_21:42:24.502703_J0KMDX_N": {
      "neighbors": {},
      "event_id": {},
      "cumulative_intake_sum_since_reset": 0,
      "cumulative_fire_count": 0,
      "cumulative_fire_count_inst": 0,
      "cumulative_intake_total": 0,
      "cumulative_intake_count": 0,
      "consecutive_fire_cnt": 0,
      "snooze_till_burst_num": 0,
      "last_burst_num": 0,
      "location": [
         517,
         586,
         296
      ],
      "block": [
         52,
         59,
         30
      ],
      "status": "Passive",
      "last_timer_reset_time": "2018-04-21 21:42:24.502731",
      "firing_pattern_id": "",
      "activation_function_id": "",
      "timer_threshold": 50,
      "firing_threshold": 1
   },
   "2018-04-21_21:42:24.502739_ADKWG5_N": {
      "neighbors": {},
      "event_id": {},
      "cumulative_intake_sum_since_reset": 0,
      "cumulative_fire_count": 0,
      "cumulative_fire_count_inst": 0,
      "cumulative_intake_total": 0,
      "cumulative_intake_count": 0,
      "consecutive_fire_cnt": 0,
      "snooze_till_burst_num": 0,
      "last_burst_num": 0,
      "location": [
         697,
         191,
         487
      ],
      "block": [
         70,
         20,
         49
      ],
      "status": "Passive",
      "last_timer_reset_time": "2018-04-21 21:42:24.502763",
      "firing_pattern_id": "",
      "activation_function_id": "",
      "timer_threshold": 50,
      "firing_threshold": 1
   },
   "2018-04-21_21:42:24.502770_AJO28Z_N": {
      "neighbors": {},
      "event_id": {},
      "cumulative_intake_sum_since_reset": 0,
      "cumulative_fire_count": 0,
      "cumulative_fire_count_inst": 0,
      "cumulative_intake_total": 0,
      "cumulative_intake_count": 0,
      "consecutive_fire_cnt": 0,
      "snooze_till_burst_num": 0,
      "last_burst_num": 0,
      "location": [
         799,
         328,
         241
      ],
      "block": [
         80,
         33,
         25
      ],
      "status": "Passive",
      "last_timer_reset_time": "2018-04-21 21:42:24.502793",
      "firing_pattern_id": "",
      "activation_function_id": "",
      "timer_threshold": 50,
      "firing_threshold": 1
   },
   "2018-04-21_21:42:24.502800_14358G_N": {
      "neighbors": {},
      "event_id": {},
      "cumulative_intake_sum_since_reset": 0,
      "cumulative_fire_count": 0,
      "cumulative_fire_count_inst": 0,
      "cumulative_intake_total": 0,
      "cumulative_intake_count": 0,
      "consecutive_fire_cnt": 0,
      "snooze_till_burst_num": 0,
      "last_burst_num": 0,
      "location": [
         879,
         245,
         253
      ],
      "block": [
         88,
         25,
         26
      ],
      "status": "Passive",
      "last_timer_reset_time": "2018-04-21 21:42:24.502822",
      "firing_pattern_id": "",
      "activation_function_id": "",
      "timer_threshold": 50,
      "firing_threshold": 1
   },
   "2018-04-21_21:42:24.502829_2NW6QA_N": {
      "neighbors": {},
      "event_id": {},
      "cumulative_intake_sum_since_reset": 0,
      "cumulative_fire_count": 0,
      "cumulative_fire_count_inst": 0,
      "cumulative_intake_total": 0,
      "cumulative_intake_count": 0,
      "consecutive_fire_cnt": 0,
      "snooze_till_burst_num": 0,
      "last_burst_num": 0,
      "location": [
         985,
         997,
         487
      ],
      "block": [
         99,
         100,
         49
      ],
      "status": "Passive",
      "last_timer_reset_time": "2018-04-21 21:42:24.502851",
      "firing_pattern_id": "",
      "activation_function_id": "",
      "timer_threshold": 50,
      "firing_threshold": 1
   },
   "2018-04-21_21:42:24.502859_R1MWZF_N": {
      "neighbors": {},
      "event_id": {},
      "cumulative_intake_sum_since_reset": 0,
      "cumulative_fire_count": 0,
      "cumulative_fire_count_inst": 0,
      "cumulative_intake_total": 0,
      "cumulative_intake_count": 0,
      "consecutive_fire_cnt": 0,
      "snooze_till_burst_num": 0,
      "last_burst_num": 0,
      "location": [
         3,
         20,
         189
      ],
      "block": [
         1,
         2,
         19
      ],
      "status": "Passive",
      "last_timer_reset_time": "2018-04-21 21:42:24.502880",
      "firing_pattern_id": "",
      "activation_function_id": "",
      "timer_threshold": 50,
      "firing_threshold": 1
   },
   "2018-04-21_21:42:24.502887_YKXJIG_N": {
      "neighbors": {},
      "event_id": {},
      "cumulative_intake_sum_since_reset": 0,
      "cumulative_fire_count": 0,
      "cumulative_fire_count_inst": 0,
      "cumulative_intake_total": 0,
      "cumulative_intake_count": 0,
      "consecutive_fire_cnt": 0,
      "snooze_till_burst_num": 0,
      "last_burst_num": 0,
      "location": [
         838,
         847,
         61
      ],
      "block": [
         84,
         85,
         7
      ],
      "status": "Passive",
      "last_timer_reset_time": "2018-04-21 21:42:24.502913",
      "firing_pattern_id": "",
      "activation_function_id": "",
      "timer_threshold": 50,
      "firing_threshold": 1
   },
   "2018-04-21_21:42:24.502922_PEIUT8_N": {
      "neighbors": {},
      "event_id": {},
      "cumulative_intake_sum_since_reset": 0,
      "cumulative_fire_count": 0,
      "cumulative_fire_count_inst": 0,
      "cumulative_intake_total": 0,
      "cumulative_intake_count": 0,
      "consecutive_fire_cnt": 0,
      "snooze_till_burst_num": 0,
      "last_burst_num": 0,
      "location": [
         144,
         293,
         585
      ],
      "block": [
         15,
         30,
         59
      ],
      "status": "Passive",
      "last_timer_reset_time": "2018-04-21 21:42:24.502950",
      "firing_pattern_id": "",
      "activation_function_id": "",
      "timer_threshold": 50,
      "firing_threshold": 1
   },
   "2018-04-21_21:42:24.502959_DZAQZP_N": {
      "neighbors": {},
      "event_id": {},
      "cumulative_intake_sum_since_reset": 0,
      "cumulative_fire_count": 0,
      "cumulative_fire_count_inst": 0,
      "cumulative_intake_total": 0,
      "cumulative_intake_count": 0,
      "consecutive_fire_cnt": 0,
      "snooze_till_burst_num": 0,
      "last_burst_num": 0,
      "location": [
         814,
         722,
         634
      ],
      "block": [
         82,
         73,
         64
      ],
      "status": "Passive",
      "last_timer_reset_time": "2018-04-21 21:42:24.502981",
      "firing_pattern_id": "",
      "activation_function_id": "",
      "timer_threshold": 50,
      "firing_threshold": 1
   },
   "2018-04-21_21:42:24.502988_EM7TOT_N": {
      "neighbors": {},
      "event_id": {},
      "cumulative_intake_sum_since_reset": 0,
      "cumulative_fire_count": 0,
      "cumulative_fire_count_inst": 0,
      "cumulative_intake_total": 0,
      "cumulative_intake_count": 0,
      "consecutive_fire_cnt": 0,
      "snooze_till_burst_num": 0,
      "last_burst_num": 0,
      "location": [
         250,
         508,
         458
      ],
      "block": [
         25,
         51,
         46
      ],
      "status": "Passive",
      "last_timer_reset_time": "2018-04-21 21:42:24.503011",
      "firing_pattern_id": "",
      "activation_function_id": "",
      "timer_threshold": 50,
      "firing_threshold": 1
   },
   "2018-04-21_21:42:24.503018_LVLHEB_N": {
      "neighbors": {},
      "event_id": {},
      "cumulative_intake_sum_since_reset": 0,
      "cumulative_fire_count": 0,
      "cumulative_fire_count_inst": 0,
      "cumulative_intake_total": 0,
      "cumulative_intake_count": 0,
      "consecutive_fire_cnt": 0,
      "snooze_till_burst_num": 0,
      "last_burst_num": 0,
      "location": [
         883,
         914,
         575
      ],
      "block": [
         89,
         92,
         58
      ],
      "status": "Passive",
      "last_timer_reset_time": "2018-04-21 21:42:24.503041",
      "firing_pattern_id": "",
      "activation_function_id": "",
      "timer_threshold": 50,
      "firing_threshold": 1
   },
   "2018-04-21_21:42:24.503049_SPQZRE_N": {
      "neighbors": {},
      "event_id": {},
      "cumulative_intake_sum_since_reset": 0,
      "cumulative_fire_count": 0,
      "cumulative_fire_count_inst": 0,
      "cumulative_intake_total": 0,
      "cumulative_intake_count": 0,
      "consecutive_fire_cnt": 0,
      "snooze_till_burst_num": 0,
      "last_burst_num": 0,
      "location": [
         242,
         653,
         414
      ],
      "block": [
         25,
         66,
         42
      ],
      "status": "Passive",
      "last_timer_reset_time": "2018-04-21 21:42:24.503070",
      "firing_pattern_id": "",
      "activation_function_id": "",
      "timer_threshold": 50,
      "firing_threshold": 1
   },
   "2018-04-21_21:42:24.503078_FVPOPO_N": {
      "neighbors": {},
      "event_id": {},
      "cumulative_intake_sum_since_reset": 0,
      "cumulative_fire_count": 0,
      "cumulative_fire_count_inst": 0,
      "cumulative_intake_total": 0,
      "cumulative_intake_count": 0,
      "consecutive_fire_cnt": 0,
      "snooze_till_burst_num": 0,
      "last_burst_num": 0,
      "location": [
         472,
         674,
         322
      ],
      "block": [
         48,
         68,
         33
      ],
      "status": "Passive",
      "last_timer_reset_time": "2018-04-21 21:42:24.503104",
      "firing_pattern_id": "",
      "activation_function_id": "",
      "timer_threshold": 50,
      "firing_threshold": 1
   },
   "2018-04-21_21:42:24.503113_F4BXQ8_N": {
      "neighbors": {},
      "event_id": {},
      "cumulative_intake_sum_since_reset": 0,
      "cumulative_fire_count": 0,
      "cumulative_fire_count_inst": 0,
      "cumulative_intake_total": 0,
      "cumulative_intake_count": 0,
      "consecutive_fire_cnt": 0,
      "snooze_till_burst_num": 0,
      "last_burst_num": 0,
      "location": [
         807,
         933,
         585
      ],
      "block": [
         81,
         94,
         59
      ],
      "status": "Passive",
      "last_timer_reset_time": "2018-04-21 21:42:24.503140",
      "firing_pattern_id": "",
      "activation_function_id": "",
      "timer_threshold": 50,
      "firing_threshold": 1
   },
   "2018-04-21_21:42:24.503149_9H4KM3_N": {
      "neighbors": {},
      "event_id": {},
      "cumulative_intake_sum_since_reset": 0,
      "cumulative_fire_count": 0,
      "cumulative_fire_count_inst": 0,
      "cumulative_intake_total": 0,
      "cumulative_intake_count": 0,
      "consecutive_fire_cnt": 0,
      "snooze_till_burst_num": 0,
      "last_burst_num": 0,
      "location": [
         814,
         603,
         647
      ],
      "block": [
         82,
         61,
         65
      ],
      "status": "Passive",
      "last_timer_reset_time": "2018-04-21 21:42:24.503172",
      "firing_pattern_id": "",
      "activation_function_id": "",
      "timer_threshold": 50,
      "firing_threshold": 1
   },
   "2018-04-21_21:42:24.503179_LANELH_N": {
      "neighbors": {},
      "event_id": {},
      "cumulative_intake_sum_since_reset": 0,
      "cumulative_fire_count": 0,
      "cumulative_fire_count_inst": 0,
      "cumulative_intake_total": 0,
      "cumulative_intake_count": 0,
      "consecutive_fire_cnt": 0,
      "snooze_till_burst_num": 0,
      "last_burst_num": 0,
      "location": [
         908,
         457,
         564
      ],
      "block": [
         91,
         46,
         57
      ],
      "status": "Passive",
      "last_timer_reset_time": "2018-04-21 21:42:24.503201",
      "firing_pattern_id": "",
      "activation_function_id": "",
      "timer_threshold": 50,
      "firing_threshold": 1
   },
   "2018-04-21_21:42:24.503209_WLRH5L_N": {
      "neighbors": {},
      "event_id": {},
      "cumulative_intake_sum_since_reset": 0,
      "cumulative_fire_count": 0,
      "cumulative_fire_count_inst": 0,
      "cumulative_intake_total": 0,
      "cumulative_intake_count": 0,
      "consecutive_fire_cnt": 0,
      "snooze_till_burst_num": 0,
      "last_burst_num": 0,
      "location": [
         10,
         8,
         444
      ],
      "block": [
         1,
         1,
         45
      ],
      "status": "Passive",
      "last_timer_reset_time": "2018-04-21 21:42:24.503231",
      "firing_pattern_id": "",
      "activation_function_id": "",
      "timer_threshold": 50,
      "firing_threshold": 1
   },
   "2018-04-21_21:42:24.503238_CAITKM_N": {
      "neighbors": {},
      "event_id": {},
      "cumulative_intake_sum_since_reset": 0,
      "cumulative_fire_count": 0,
      "cumulative_fire_count_inst": 0,
      "cumulative_intake_total": 0,
      "cumulative_intake_count": 0,
      "consecutive_fire_cnt": 0,
      "snooze_till_burst_num": 0,
      "last_burst_num": 0,
      "location": [
         884,
         558,
         261
      ],
      "block": [
         89,
         56,
         27
      ],
      "status": "Passive",
      "last_timer_reset_time": "2018-04-21 21:42:24.503259",
      "firing_pattern_id": "",
      "activation_function_id": "",
      "timer_threshold": 50,
      "firing_threshold": 1
   },
   "2018-04-21_21:42:24.503267_JQ1C4U_N": {
      "neighbors": {},
      "event_id": {},
      "cumulative_intake_sum_since_reset": 0,
      "cumulative_fire_count": 0,
      "cumulative_fire_count_inst": 0,
      "cumulative_intake_total": 0,
      "cumulative_intake_count": 0,
      "consecutive_fire_cnt": 0,
      "snooze_till_burst_num": 0,
      "last_burst_num": 0,
      "location": [
         9,
         320,
         567
      ],
      "block": [
         1,
         32,
         57
      ],
      "status": "Passive",
      "last_timer_reset_time": "2018-04-21 21:42:24.503289",
      "firing_pattern_id": "",
      "activation_function_id": "",
      "timer_threshold": 50,
      "firing_threshold": 1
   },
   "2018-04-21_21:42:24.503296_OBISIH_N": {
      "neighbors": {},
      "event_id": {},
      "cumulative_intake_sum_since_reset": 0,
      "cumulative_fire_count": 0,
      "cumulative_fire_count_inst": 0,
      "cumulative_intake_total": 0,
      "cumulative_intake_count": 0,
      "consecutive_fire_cnt": 0,
      "snooze_till_burst_num": 0,
      "last_burst_num": 0,
      "location": [
         583,
         450,
         56
      ],
      "block": [
         59,
         45,
         6
      ],
      "status": "Passive",
      "last_timer_reset_time": "2018-04-21 21:42:24.503318",
      "firing_pattern_id": "",
      "activation_function_id": "",
      "timer_threshold": 50,
      "firing_threshold": 1
   },
   "2018-04-21_21:42:24.503325_0ICZ88_N": {
      "neighbors": {},
      "event_id": {},
      "cumulative_intake_sum_since_reset": 0,
      "cumulative_fire_count": 0,
      "cumulative_fire_count_inst": 0,
      "cumulative_intake_total": 0,
      "cumulative_intake_count": 0,
      "consecutive_fire_cnt": 0,
      "snooze_till_burst_num": 0,
      "last_burst_num": 0,
      "location": [
         900,
         222,
         14
      ],
      "block": [
         90,
         23,
         2
      ],
      "status": "Passive",
      "last_timer_reset_time": "2018-04-21 21:42:24.503353",
      "firing_pattern_id": "",
      "activation_function_id": "",
      "timer_threshold": 50,
      "firing_threshold": 1
   },
   "2018-04-21_21:42:24.503362_VN4ZXX_N": {
      "neighbors": {},
      "event_id": {},
      "cumulative_intake_sum_since_reset": 0,
      "cumulative_fire_count": 0,
      "cumulative_fire_count_inst": 0,
      "cumulative_intake_total": 0,
      "cumulative_intake_count": 0,
      "consecutive_fire_cnt": 0,
      "snooze_till_burst_num": 0,
      "last_burst_num": 0,
      "location": [
         524,
         293,
         125
      ],
      "block": [
         53,
         30,
         13
      ],
      "status": "Passive",
      "last_timer_reset_time": "2018-04-21 21:42:24.503385",
      "firing_pattern_id": "",
      "activation_function_id": "",
      "timer_threshold": 50,
      "firing_threshold": 1
   },
   "2018-04-21_21:42:24.503392_AKORYI_N": {
      "neighbors": {},
      "event_id": {},
      "cumulative_intake_sum_since_reset": 0,
      "cumulative_fire_count": 0,
      "cumulative_fire_count_inst": 0,
      "cumulative_intake_total": 0,
      "cumulative_intake_count": 0,
      "consecutive_fire_cnt": 0,
      "snooze_till_burst_num": 0,
      "last_burst_num": 0,
      "location": [
         71,
         386,
         422
      ],
      "block": [
         8,
         39,
         43
      ],
      "status": "Passive",
      "last_timer_reset_time": "2018-04-21 21:42:24.503415",
      "firing_pattern_id": "",
      "activation_function_id": "",
      "timer_threshold": 50,
      "firing_threshold": 1
   },
   "2018-04-21_21:42:24.503422_2N2E9N_N": {
      "neighbors": {},
      "event_id": {},
      "cumulative_intake_sum_since_reset": 0,
      "cumulative_fire_count": 0,
      "cumulative_fire_count_inst": 0,
      "cumulative_intake_total": 0,
      "cumulative_intake_count": 0,
      "consecutive_fire_cnt": 0,
      "snooze_till_burst_num": 0,
      "last_burst_num": 0,
      "location": [
         204,
         923,
         488
      ],
      "block": [
         21,
         93,
         49
      ],
      "status": "Passive",
      "last_timer_reset_time": "2018-04-21 21:42:24.503444",
      "firing_pattern_id": "",
      "activation_function_id": "",
      "timer_threshold": 50,
      "firing_threshold": 1
   },
   "2018-04-21_21:42:24.503451_4JJDD6_N": {
      "neighbors": {},
      "event_id": {},
      "cumulative_intake_sum_since_reset": 0,
      "cumulative_fire_count": 0,
      "cumulative_fire_count_inst": 0,
      "cumulative_intake_total": 0,
      "cumulative_intake_count": 0,
      "consecutive_fire_cnt": 0,
      "snooze_till_burst_num": 0,
      "last_burst_num": 0,
      "location": [
         481,
         481,
         607
      ],
      "block": [
         49,
         49,
         61
      ],
      "status": "Passive",
      "last_timer_reset_time": "2018-04-21 21:42:24.503478",
      "firing_pattern_id": "",
      "activation_function_id": "",
      "timer_threshold": 50,
      "firing_threshold": 1
   },
   "2018-04-21_21:42:24.503487_ETJLYT_N": {
      "neighbors": {},
      "event_id": {},
      "cumulative_intake_sum_since_reset": 0,
      "cumulative_fire_count": 0,
      "cumulative_fire_count_inst": 0,
      "cumulative_intake_total": 0,
      "cumulative_intake_count": 0,
      "consecutive_fire_cnt": 0,
      "snooze_till_burst_num": 0,
      "last_burst_num": 0,
      "location": [
         161,
         234,
         697
      ],
      "block": [
         17,
         24,
         70
      ],
      "status": "Passive",
      "last_timer_reset_time": "2018-04-21 21:42:24.503509",
      "firing_pattern_id": "",
      "activation_function_id": "",
      "timer_threshold": 50,
      "firing_threshold": 1
   },
   "2018-04-21_21:42:24.503517_VK03WU_N": {
      "neighbors": {},
      "event_id": {},
      "cumulative_intake_sum_since_reset": 0,
      "cumulative_fire_count": 0,
      "cumulative_fire_count_inst": 0,
      "cumulative_intake_total": 0,
      "cumulative_intake_count": 0,
      "consecutive_fire_cnt": 0,
      "snooze_till_burst_num": 0,
      "last_burst_num": 0,
      "location": [
         830,
         997,
         214
      ],
      "block": [
         83,
         100,
         22
      ],
      "status": "Passive",
      "last_timer_reset_time": "2018-04-21 21:42:24.503544",
      "firing_pattern_id": "",
      "activation_function_id": "",
      "timer_threshold": 50,
      "firing_threshold": 1
   },
   "2018-04-21_21:42:24.503553_UVMXZY_N": {
      "neighbors": {},
      "event_id": {},
      "cumulative_intake_sum_since_reset": 0,
      "cumulative_fire_count": 0,
      "cumulative_fire_count_inst": 0,
      "cumulative_intake_total": 0,
      "cumulative_intake_count": 0,
      "consecutive_fire_cnt": 0,
      "snooze_till_burst_num": 0,
      "last_burst_num": 0,
      "location": [
         662,
         206,
         312
      ],
      "block": [
         67,
         21,
         32
      ],
      "status": "Passive",
      "last_timer_reset_time": "2018-04-21 21:42:24.503581",
      "firing_pattern_id": "",
      "activation_function_id": "",
      "timer_threshold": 50,
      "firing_threshold": 1
   },
   "2018-04-21_21:42:24.503590_7N7K9S_N": {
      "neighbors": {},
      "event_id": {},
      "cumulative_intake_sum_since_reset": 0,
      "cumulative_fire_count": 0,
      "cumulative_fire_count_inst": 0,
      "cumulative_intake_total": 0,
      "cumulative_intake_count": 0,
      "consecutive_fire_cnt": 0,
      "snooze_till_burst_num": 0,
      "last_burst_num": 0,
      "location": [
         51,
         372,
         71
      ],
      "block": [
         6,
         38,
         8
      ],
      "status": "Passive",
      "last_timer_reset_time": "2018-04-21 21:42:24.503612",
      "firing_pattern_id": "",
      "activation_function_id": "",
      "timer_threshold": 50,
      "firing_threshold": 1
   },
   "2018-04-21_21:42:24.503619_JNAWC4_N": {
      "neighbors": {},
      "event_id": {},
      "cumulative_intake_sum_since_reset": 0,
      "cumulative_fire_count": 0,
      "cumulative_fire_count_inst": 0,
      "cumulative_intake_total": 0,
      "cumulative_intake_count": 0,
      "consecutive_fire_cnt": 0,
      "snooze_till_burst_num": 0,
      "last_burst_num": 0,
      "location": [
         883,
         628,
         315
      ],
      "block": [
         89,
         63,
         32
      ],
      "status": "Passive",
      "last_timer_reset_time": "2018-04-21 21:42:24.503641",
      "firing_pattern_id": "",
      "activation_function_id": "",
      "timer_threshold": 50,
      "firing_threshold": 1
   },
   "2018-04-21_21:42:24.503649_7IMX4K_N": {
      "neighbors": {},
      "event_id": {},
      "cumulative_intake_sum_since_reset": 0,
      "cumulative_fire_count": 0,
      "cumulative_fire_count_inst": 0,
      "cumulative_intake_total": 0,
      "cumulative_intake_count": 0,
      "consecutive_fire_cnt": 0,
      "snooze_till_burst_num": 0,
      "last_burst_num": 0,
      "location": [
         88,
         75,
         73
      ],
      "block": [
         9,
         8,
         8
      ],
      "status": "Passive",
      "last_timer_reset_time": "2018-04-21 21:42:24.503677",
      "firing_pattern_id": "",
      "activation_function_id": "",
      "timer_threshold": 50,
      "firing_threshold": 1
   },
   "2018-04-21_21:42:24.503685_MIH1PZ_N": {
      "neighbors": {},
      "event_id": {},
      "cumulative_intake_sum_since_reset": 0,
      "cumulative_fire_count": 0,
      "cumulative_fire_count_inst": 0,
      "cumulative_intake_total": 0,
      "cumulative_intake_count": 0,
      "consecutive_fire_cnt": 0,
      "snooze_till_burst_num": 0,
      "last_burst_num": 0,
      "location": [
         886,
         574,
         100
      ],
      "block": [
         89,
         58,
         10
      ],
      "status": "Passive",
      "last_timer_reset_time": "2018-04-21 21:42:24.503708",
      "firing_pattern_id": "",
      "activation_function_id": "",
      "timer_threshold": 50,
      "firing_threshold": 1
   },
   "2018-04-21_21:42:24.503715_0EV3BU_N": {
      "neighbors": {},
      "event_id": {},
      "cumulative_intake_sum_since_reset": 0,
      "cumulative_fire_count": 0,
      "cumulative_fire_count_inst": 0,
      "cumulative_intake_total": 0,
      "cumulative_intake_count": 0,
      "consecutive_fire_cnt": 0,
      "snooze_till_burst_num": 0,
      "last_burst_num": 0,
      "location": [
         106,
         486,
         111
      ],
      "block": [
         11,
         49,
         12
      ],
      "status": "Passive",
      "last_timer_reset_time": "2018-04-21 21:42:24.503737",
      "firing_pattern_id": "",
      "activation_function_id": "",
      "timer_threshold": 50,
      "firing_threshold": 1
   },
   "2018-04-21_21:42:24.503745_KR68JS_N": {
      "neighbors": {},
      "event_id": {},
      "cumulative_intake_sum_since_reset": 0,
      "cumulative_fire_count": 0,
      "cumulative_fire_count_inst": 0,
      "cumulative_intake_total": 0,
      "cumulative_intake_count": 0,
      "consecutive_fire_cnt": 0,
      "snooze_till_burst_num": 0,
      "last_burst_num": 0,
      "location": [
         805,
         829,
         323
      ],
      "block": [
         81,
         83,
         33
      ],
      "status": "Passive",
      "last_timer_reset_time": "2018-04-21 21:42:24.503766",
      "firing_pattern_id": "",
      "activation_function_id": "",
      "timer_threshold": 50,
      "firing_threshold": 1
   },
   "2018-04-21_21:42:24.503773_8AU681_N": {
      "neighbors": {},
      "event_id": {},
      "cumulative_intake_sum_since_reset": 0,
      "cumulative_fire_count": 0,
      "cumulative_fire_count_inst": 0,
      "cumulative_intake_total": 0,
      "cumulative_intake_count": 0,
      "consecutive_fire_cnt": 0,
      "snooze_till_burst_num": 0,
      "last_burst_num": 0,
      "location": [
         942,
         909,
         630
      ],
      "block": [
         95,
         91,
         63
      ],
      "status": "Passive",
      "last_timer_reset_time": "2018-04-21 21:42:24.503800",
      "firing_pattern_id": "",
      "activation_function_id": "",
      "timer_threshold": 50,
      "firing_threshold": 1
   },
   "2018-04-21_21:42:24.503809_HWKS1I_N": {
      "neighbors": {},
      "event_id": {},
      "cumulative_intake_sum_since_reset": 0,
      "cumulative_fire_count": 0,
      "cumulative_fire_count_inst": 0,
      "cumulative_intake_total": 0,
      "cumulative_intake_count": 0,
      "consecutive_fire_cnt": 0,
      "snooze_till_burst_num": 0,
      "last_burst_num": 0,
      "location": [
         837,
         478,
         197
      ],
      "block": [
         84,
         48,
         20
      ],
      "status": "Passive",
      "last_timer_reset_time": "2018-04-21 21:42:24.503832",
      "firing_pattern_id": "",
      "activation_function_id": "",
      "timer_threshold": 50,
      "firing_threshold": 1
   },
   "2018-04-21_21:42:24.503839_NAPXTV_N": {
      "neighbors": {},
      "event_id": {},
      "cumulative_intake_sum_since_reset": 0,
      "cumulative_fire_count": 0,
      "cumulative_fire_count_inst": 0,
      "cumulative_intake_total": 0,
      "cumulative_intake_count": 0,
      "consecutive_fire_cnt": 0,
      "snooze_till_burst_num": 0,
      "last_burst_num": 0,
      "location": [
         517,
         302,
         297
      ],
      "block": [
         52,
         31,
         30
      ],
      "status": "Passive",
      "last_timer_reset_time": "2018-04-21 21:42:24.503866",
      "firing_pattern_id": "",
      "activation_function_id": "",
      "timer_threshold": 50,
      "firing_threshold": 1
   },
   "2018-04-21_21:42:24.503875_G9A727_N": {
      "neighbors": {},
      "event_id": {},
      "cumulative_intake_sum_since_reset": 0,
      "cumulative_fire_count": 0,
      "cumulative_fire_count_inst": 0,
      "cumulative_intake_total": 0,
      "cumulative_intake_count": 0,
      "consecutive_fire_cnt": 0,
      "snooze_till_burst_num": 0,
      "last_burst_num": 0,
      "location": [
         316,
         392,
         170
      ],
      "block": [
         32,
         40,
         17
      ],
      "status": "Passive",
      "last_timer_reset_time": "2018-04-21 21:42:24.503898",
      "firing_pattern_id": "",
      "activation_function_id": "",
      "timer_threshold": 50,
      "firing_threshold": 1
   },
   "2018-04-21_21:42:24.503905_FXW6ND_N": {
      "neighbors": {},
      "event_id": {},
      "cumulative_intake_sum_since_reset": 0,
      "cumulative_fire_count": 0,
      "cumulative_fire_count_inst": 0,
      "cumulative_intake_total": 0,
      "cumulative_intake_count": 0,
      "consecutive_fire_cnt": 0,
      "snooze_till_burst_num": 0,
      "last_burst_num": 0,
      "location": [
         626,
         552,
         693
      ],
      "block": [
         63,
         56,
         70
      ],
      "status": "Passive",
      "last_timer_reset_time": "2018-04-21 21:42:24.503932",
      "firing_pattern_id": "",
      "activation_function_id": "",
      "timer_threshold": 50,
      "firing_threshold": 1
   },
   "2018-04-21_21:42:24.503940_3R545M_N": {
      "neighbors": {},
      "event_id": {},
      "cumulative_intake_sum_since_reset": 0,
      "cumulative_fire_count": 0,
      "cumulative_fire_count_inst": 0,
      "cumulative_intake_total": 0,
      "cumulative_intake_count": 0,
      "consecutive_fire_cnt": 0,
      "snooze_till_burst_num": 0,
      "last_burst_num": 0,
      "location": [
         14,
         239,
         635
      ],
      "block": [
         2,
         24,
         64
      ],
      "status": "Passive",
      "last_timer_reset_time": "2018-04-21 21:42:24.503963",
      "firing_pattern_id": "",
      "activation_function_id": "",
      "timer_threshold": 50,
      "firing_threshold": 1
   },
   "2018-04-21_21:42:24.503970_RGWAIB_N": {
      "neighbors": {},
      "event_id": {},
      "cumulative_intake_sum_since_reset": 0,
      "cumulative_fire_count": 0,
      "cumulative_fire_count_inst": 0,
      "cumulative_intake_total": 0,
      "cumulative_intake_count": 0,
      "consecutive_fire_cnt": 0,
      "snooze_till_burst_num": 0,
      "last_burst_num": 0,
      "location": [
         701,
         233,
         590
      ],
      "block": [
         71,
         24,
         59
      ],
      "status": "Passive",
      "last_timer_reset_time": "2018-04-21 21:42:24.503991",
      "firing_pattern_id": "",
      "activation_function_id": "",
      "timer_threshold": 50,
      "firing_threshold": 1
   },
   "2018-04-21_21:42:24.503998_8CC6GA_N": {
      "neighbors": {},
      "event_id": {},
      "cumulative_intake_sum_since_reset": 0,
      "cumulative_fire_count": 0,
      "cumulative_fire_count_inst": 0,
      "cumulative_intake_total": 0,
      "cumulative_intake_count": 0,
      "consecutive_fire_cnt": 0,
      "snooze_till_burst_num": 0,
      "last_burst_num": 0,
      "location": [
         209,
         924,
         404
      ],
      "block": [
         21,
         93,
         41
      ],
      "status": "Passive",
      "last_timer_reset_time": "2018-04-21 21:42:24.504026",
      "firing_pattern_id": "",
      "activation_function_id": "",
      "timer_threshold": 50,
      "firing_threshold": 1
   },
   "2018-04-21_21:42:24.504035_S0A99Z_N": {
      "neighbors": {},
      "event_id": {},
      "cumulative_intake_sum_since_reset": 0,
      "cumulative_fire_count": 0,
      "cumulative_fire_count_inst": 0,
      "cumulative_intake_total": 0,
      "cumulative_intake_count": 0,
      "consecutive_fire_cnt": 0,
      "snooze_till_burst_num": 0,
      "last_burst_num": 0,
      "location": [
         505,
         560,
         684
      ],
      "block": [
         51,
         56,
         69
      ],
      "status": "Passive",
      "last_timer_reset_time": "2018-04-21 21:42:24.504058",
      "firing_pattern_id": "",
      "activation_function_id": "",
      "timer_threshold": 50,
      "firing_threshold": 1
   },
   "2018-04-21_21:42:24.504066_P3VI8O_N": {
      "neighbors": {},
      "event_id": {},
      "cumulative_intake_sum_since_reset": 0,
      "cumulative_fire_count": 0,
      "cumulative_fire_count_inst": 0,
      "cumulative_intake_total": 0,
      "cumulative_intake_count": 0,
      "consecutive_fire_cnt": 0,
      "snooze_till_burst_num": 0,
      "last_burst_num": 0,
      "location": [
         627,
         622,
         530
      ],
      "block": [
         63,
         63,
         53
      ],
      "status": "Passive",
      "last_timer_reset_time": "2018-04-21 21:42:24.504087",
      "firing_pattern_id": "",
      "activation_function_id": "",
      "timer_threshold": 50,
      "firing_threshold": 1
   },
   "2018-04-21_21:42:24.504095_BPQL8H_N": {
      "neighbors": {},
      "event_id": {},
      "cumulative_intake_sum_since_reset": 0,
      "cumulative_fire_count": 0,
      "cumulative_fire_count_inst": 0,
      "cumulative_intake_total": 0,
      "cumulative_intake_count": 0,
      "consecutive_fire_cnt": 0,
      "snooze_till_burst_num": 0,
      "last_burst_num": 0,
      "location": [
         984,
         971,
         191
      ],
      "block": [
         99,
         98,
         20
      ],
      "status": "Passive",
      "last_timer_reset_time": "2018-04-21 21:42:24.504161",
      "firing_pattern_id": "",
      "activation_function_id": "",
      "timer_threshold": 50,
      "firing_threshold": 1
   },
   "2018-04-21_21:42:24.504171_019BAS_N": {
      "neighbors": {},
      "event_id": {},
      "cumulative_intake_sum_since_reset": 0,
      "cumulative_fire_count": 0,
      "cumulative_fire_count_inst": 0,
      "cumulative_intake_total": 0,
      "cumulative_intake_count": 0,
      "consecutive_fire_cnt": 0,
      "snooze_till_burst_num": 0,
      "last_burst_num": 0,
      "location": [
         161,
         638,
         250
      ],
      "block": [
         17,
         64,
         25
      ],
      "status": "Passive",
      "last_timer_reset_time": "2018-04-21 21:42:24.504195",
      "firing_pattern_id": "",
      "activation_function_id": "",
      "timer_threshold": 50,
      "firing_threshold": 1
   },
   "2018-04-21_21:42:24.504202_0K86AF_N": {
      "neighbors": {},
      "event_id": {},
      "cumulative_intake_sum_since_reset": 0,
      "cumulative_fire_count": 0,
      "cumulative_fire_count_inst": 0,
      "cumulative_intake_total": 0,
      "cumulative_intake_count": 0,
      "consecutive_fire_cnt": 0,
      "snooze_till_burst_num": 0,
      "last_burst_num": 0,
      "location": [
         739,
         29,
         508
      ],
      "block": [
         74,
         3,
         51
      ],
      "status": "Passive",
      "last_timer_reset_time": "2018-04-21 21:42:24.504224",
      "firing_pattern_id": "",
      "activation_function_id": "",
      "timer_threshold": 50,
      "firing_threshold": 1
   },
   "2018-04-21_21:42:24.504231_O6ZUDR_N": {
      "neighbors": {},
      "event_id": {},
      "cumulative_intake_sum_since_reset": 0,
      "cumulative_fire_count": 0,
      "cumulative_fire_count_inst": 0,
      "cumulative_intake_total": 0,
      "cumulative_intake_count": 0,
      "consecutive_fire_cnt": 0,
      "snooze_till_burst_num": 0,
      "last_burst_num": 0,
      "location": [
         100,
         328,
         52
      ],
      "block": [
         10,
         33,
         6
      ],
      "status": "Passive",
      "last_timer_reset_time": "2018-04-21 21:42:24.504252",
      "firing_pattern_id": "",
      "activation_function_id": "",
      "timer_threshold": 50,
      "firing_threshold": 1
   },
   "2018-04-21_21:42:24.504260_5RE5BB_N": {
      "neighbors": {},
      "event_id": {},
      "cumulative_intake_sum_since_reset": 0,
      "cumulative_fire_count": 0,
      "cumulative_fire_count_inst": 0,
      "cumulative_intake_total": 0,
      "cumulative_intake_count": 0,
      "consecutive_fire_cnt": 0,
      "snooze_till_burst_num": 0,
      "last_burst_num": 0,
      "location": [
         401,
         736,
         550
      ],
      "block": [
         41,
         74,
         55
      ],
      "status": "Passive",
      "last_timer_reset_time": "2018-04-21 21:42:24.504290",
      "firing_pattern_id": "",
      "activation_function_id": "",
      "timer_threshold": 50,
      "firing_threshold": 1
   },
   "2018-04-21_21:42:24.504299_PPQGHT_N": {
      "neighbors": {},
      "event_id": {},
      "cumulative_intake_sum_since_reset": 0,
      "cumulative_fire_count": 0,
      "cumulative_fire_count_inst": 0,
      "cumulative_intake_total": 0,
      "cumulative_intake_count": 0,
      "consecutive_fire_cnt": 0,
      "snooze_till_burst_num": 0,
      "last_burst_num": 0,
      "location": [
         536,
         518,
         198
      ],
      "block": [
         54,
         52,
         20
      ],
      "status": "Passive",
      "last_timer_reset_time": "2018-04-21 21:42:24.504322",
      "firing_pattern_id": "",
      "activation_function_id": "",
      "timer_threshold": 50,
      "firing_threshold": 1
   },
   "2018-04-21_21:42:24.504329_R56TH5_N": {
      "neighbors": {},
      "event_id": {},
      "cumulative_intake_sum_since_reset": 0,
      "cumulative_fire_count": 0,
      "cumulative_fire_count_inst": 0,
      "cumulative_intake_total": 0,
      "cumulative_intake_count": 0,
      "consecutive_fire_cnt": 0,
      "snooze_till_burst_num": 0,
      "last_burst_num": 0,
      "location": [
         723,
         501,
         41
      ],
      "block": [
         73,
         51,
         5
      ],
      "status": "Passive",
      "last_timer_reset_time": "2018-04-21 21:42:24.504351",
      "firing_pattern_id": "",
      "activation_function_id": "",
      "timer_threshold": 50,
      "firing_threshold": 1
   },
   "2018-04-21_21:42:24.504358_C9YMW4_N": {
      "neighbors": {},
      "event_id": {},
      "cumulative_intake_sum_since_reset": 0,
      "cumulative_fire_count": 0,
      "cumulative_fire_count_inst": 0,
      "cumulative_intake_total": 0,
      "cumulative_intake_count": 0,
      "consecutive_fire_cnt": 0,
      "snooze_till_burst_num": 0,
      "last_burst_num": 0,
      "location": [
         659,
         944,
         316
      ],
      "block": [
         66,
         95,
         32
      ],
      "status": "Passive",
      "last_timer_reset_time": "2018-04-21 21:42:24.504380",
      "firing_pattern_id": "",
      "activation_function_id": "",
      "timer_threshold": 50,
      "firing_threshold": 1
   },
   "2018-04-21_21:42:24.504387_UMPT4I_N": {
      "neighbors": {},
      "event_id": {},
      "cumulative_intake_sum_since_reset": 0,
      "cumulative_fire_count": 0,
      "cumulative_fire_count_inst": 0,
      "cumulative_intake_total": 0,
      "cumulative_intake_count": 0,
      "consecutive_fire_cnt": 0,
      "snooze_till_burst_num": 0,
      "last_burst_num": 0,
      "location": [
         597,
         593,
         383
      ],
      "block": [
         60,
         60,
         39
      ],
      "status": "Passive",
      "last_timer_reset_time": "2018-04-21 21:42:24.504409",
      "firing_pattern_id": "",
      "activation_function_id": "",
      "timer_threshold": 50,
      "firing_threshold": 1
   },
   "2018-04-21_21:42:24.504416_ETSEJ2_N": {
      "neighbors": {},
      "event_id": {},
      "cumulative_intake_sum_since_reset": 0,
      "cumulative_fire_count": 0,
      "cumulative_fire_count_inst": 0,
      "cumulative_intake_total": 0,
      "cumulative_intake_count": 0,
      "consecutive_fire_cnt": 0,
      "snooze_till_burst_num": 0,
      "last_burst_num": 0,
      "location": [
         508,
         503,
         516
      ],
      "block": [
         51,
         51,
         52
      ],
      "status": "Passive",
      "last_timer_reset_time": "2018-04-21 21:42:24.504440",
      "firing_pattern_id": "",
      "activation_function_id": "",
      "timer_threshold": 50,
      "firing_threshold": 1
   },
   "2018-04-21_21:42:24.504448_GZDYGF_N": {
      "neighbors": {},
      "event_id": {},
      "cumulative_intake_sum_since_reset": 0,
      "cumulative_fire_count": 0,
      "cumulative_fire_count_inst": 0,
      "cumulative_intake_total": 0,
      "cumulative_intake_count": 0,
      "consecutive_fire_cnt": 0,
      "snooze_till_burst_num": 0,
      "last_burst_num": 0,
      "location": [
         110,
         570,
         532
      ],
      "block": [
         11,
         57,
         54
      ],
      "status": "Passive",
      "last_timer_reset_time": "2018-04-21 21:42:24.504469",
      "firing_pattern_id": "",
      "activation_function_id": "",
      "timer_threshold": 50,
      "firing_threshold": 1
   },
   "2018-04-21_21:42:24.504476_G19KP8_N": {
      "neighbors": {},
      "event_id": {},
      "cumulative_intake_sum_since_reset": 0,
      "cumulative_fire_count": 0,
      "cumulative_fire_count_inst": 0,
      "cumulative_intake_total": 0,
      "cumulative_intake_count": 0,
      "consecutive_fire_cnt": 0,
      "snooze_till_burst_num": 0,
      "last_burst_num": 0,
      "location": [
         686,
         252,
         34
      ],
      "block": [
         69,
         26,
         4
      ],
      "status": "Passive",
      "last_timer_reset_time": "2018-04-21 21:42:24.504497",
      "firing_pattern_id": "",
      "activation_function_id": "",
      "timer_threshold": 50,
      "firing_threshold": 1
   },
   "2018-04-21_21:42:24.504505_U2Y8XY_N": {
      "neighbors": {},
      "event_id": {},
      "cumulative_intake_sum_since_reset": 0,
      "cumulative_fire_count": 0,
      "cumulative_fire_count_inst": 0,
      "cumulative_intake_total": 0,
      "cumulative_intake_count": 0,
      "consecutive_fire_cnt": 0,
      "snooze_till_burst_num": 0,
      "last_burst_num": 0,
      "location": [
         837,
         573,
         523
      ],
      "block": [
         84,
         58,
         53
      ],
      "status": "Passive",
      "last_timer_reset_time": "2018-04-21 21:42:24.504530",
      "firing_pattern_id": "",
      "activation_function_id": "",
      "timer_threshold": 50,
      "firing_threshold": 1
   },
   "2018-04-21_21:42:24.504539_CT9KTG_N": {
      "neighbors": {
         "2018-04-21_21:42:24.540047_C0SBWE_N": {
            "cortical_area": "vision_IT",
            "synaptic_strength": 0.5
         }
      },
      "event_id": {},
      "cumulative_intake_sum_since_reset": 0,
      "cumulative_fire_count": 0,
      "cumulative_fire_count_inst": 0,
      "cumulative_intake_total": 0,
      "cumulative_intake_count": 0,
      "consecutive_fire_cnt": 0,
      "snooze_till_burst_num": 0,
      "last_burst_num": 0,
      "location": [
         774,
         606,
         233
      ],
      "block": [
         78,
         61,
         24
      ],
      "status": "Passive",
      "last_timer_reset_time": "2018-04-21 21:42:24.504562",
      "firing_pattern_id": "",
      "activation_function_id": "",
      "timer_threshold": 50,
      "firing_threshold": 1
   },
   "2018-04-21_21:42:24.504570_RLQLH6_N": {
      "neighbors": {},
      "event_id": {},
      "cumulative_intake_sum_since_reset": 0,
      "cumulative_fire_count": 0,
      "cumulative_fire_count_inst": 0,
      "cumulative_intake_total": 0,
      "cumulative_intake_count": 0,
      "consecutive_fire_cnt": 0,
      "snooze_till_burst_num": 0,
      "last_burst_num": 0,
      "location": [
         678,
         515,
         379
      ],
      "block": [
         68,
         52,
         38
      ],
      "status": "Passive",
      "last_timer_reset_time": "2018-04-21 21:42:24.504592",
      "firing_pattern_id": "",
      "activation_function_id": "",
      "timer_threshold": 50,
      "firing_threshold": 1
   },
   "2018-04-21_21:42:24.504599_JGWYLP_N": {
      "neighbors": {},
      "event_id": {},
      "cumulative_intake_sum_since_reset": 0,
      "cumulative_fire_count": 0,
      "cumulative_fire_count_inst": 0,
      "cumulative_intake_total": 0,
      "cumulative_intake_count": 0,
      "consecutive_fire_cnt": 0,
      "snooze_till_burst_num": 0,
      "last_burst_num": 0,
      "location": [
         414,
         518,
         33
      ],
      "block": [
         42,
         52,
         4
      ],
      "status": "Passive",
      "last_timer_reset_time": "2018-04-21 21:42:24.504621",
      "firing_pattern_id": "",
      "activation_function_id": "",
      "timer_threshold": 50,
      "firing_threshold": 1
   },
   "2018-04-21_21:42:24.504637_6PFQZ2_N": {
      "neighbors": {},
      "event_id": {},
      "cumulative_intake_sum_since_reset": 0,
      "cumulative_fire_count": 0,
      "cumulative_fire_count_inst": 0,
      "cumulative_intake_total": 0,
      "cumulative_intake_count": 0,
      "consecutive_fire_cnt": 0,
      "snooze_till_burst_num": 0,
      "last_burst_num": 0,
      "location": [
         208,
         754,
         377
      ],
      "block": [
         21,
         76,
         38
      ],
      "status": "Passive",
      "last_timer_reset_time": "2018-04-21 21:42:24.504673",
      "firing_pattern_id": "",
      "activation_function_id": "",
      "timer_threshold": 50,
      "firing_threshold": 1
   },
   "2018-04-21_21:42:24.504682_N4Y0AC_N": {
      "neighbors": {},
      "event_id": {},
      "cumulative_intake_sum_since_reset": 0,
      "cumulative_fire_count": 0,
      "cumulative_fire_count_inst": 0,
      "cumulative_intake_total": 0,
      "cumulative_intake_count": 0,
      "consecutive_fire_cnt": 0,
      "snooze_till_burst_num": 0,
      "last_burst_num": 0,
      "location": [
         807,
         673,
         519
      ],
      "block": [
         81,
         68,
         52
      ],
      "status": "Passive",
      "last_timer_reset_time": "2018-04-21 21:42:24.504709",
      "firing_pattern_id": "",
      "activation_function_id": "",
      "timer_threshold": 50,
      "firing_threshold": 1
   },
   "2018-04-21_21:42:24.504717_GVJ59X_N": {
      "neighbors": {},
      "event_id": {},
      "cumulative_intake_sum_since_reset": 0,
      "cumulative_fire_count": 0,
      "cumulative_fire_count_inst": 0,
      "cumulative_intake_total": 0,
      "cumulative_intake_count": 0,
      "consecutive_fire_cnt": 0,
      "snooze_till_burst_num": 0,
      "last_burst_num": 0,
      "location": [
         282,
         317,
         215
      ],
      "block": [
         29,
         32,
         22
      ],
      "status": "Passive",
      "last_timer_reset_time": "2018-04-21 21:42:24.504740",
      "firing_pattern_id": "",
      "activation_function_id": "",
      "timer_threshold": 50,
      "firing_threshold": 1
   },
   "2018-04-21_21:42:24.504748_5SLWN5_N": {
      "neighbors": {},
      "event_id": {},
      "cumulative_intake_sum_since_reset": 0,
      "cumulative_fire_count": 0,
      "cumulative_fire_count_inst": 0,
      "cumulative_intake_total": 0,
      "cumulative_intake_count": 0,
      "consecutive_fire_cnt": 0,
      "snooze_till_burst_num": 0,
      "last_burst_num": 0,
      "location": [
         31,
         540,
         203
      ],
      "block": [
         4,
         54,
         21
      ],
      "status": "Passive",
      "last_timer_reset_time": "2018-04-21 21:42:24.504782",
      "firing_pattern_id": "",
      "activation_function_id": "",
      "timer_threshold": 50,
      "firing_threshold": 1
   },
   "2018-04-21_21:42:24.504799_O9G3C0_N": {
      "neighbors": {},
      "event_id": {},
      "cumulative_intake_sum_since_reset": 0,
      "cumulative_fire_count": 0,
      "cumulative_fire_count_inst": 0,
      "cumulative_intake_total": 0,
      "cumulative_intake_count": 0,
      "consecutive_fire_cnt": 0,
      "snooze_till_burst_num": 0,
      "last_burst_num": 0,
      "location": [
         944,
         8,
         84
      ],
      "block": [
         95,
         1,
         9
      ],
      "status": "Passive",
      "last_timer_reset_time": "2018-04-21 21:42:24.504831",
      "firing_pattern_id": "",
      "activation_function_id": "",
      "timer_threshold": 50,
      "firing_threshold": 1
   },
   "2018-04-21_21:42:24.504839_8Y1WP6_N": {
      "neighbors": {},
      "event_id": {},
      "cumulative_intake_sum_since_reset": 0,
      "cumulative_fire_count": 0,
      "cumulative_fire_count_inst": 0,
      "cumulative_intake_total": 0,
      "cumulative_intake_count": 0,
      "consecutive_fire_cnt": 0,
      "snooze_till_burst_num": 0,
      "last_burst_num": 0,
      "location": [
         551,
         255,
         38
      ],
      "block": [
         56,
         26,
         4
      ],
      "status": "Passive",
      "last_timer_reset_time": "2018-04-21 21:42:24.504861",
      "firing_pattern_id": "",
      "activation_function_id": "",
      "timer_threshold": 50,
      "firing_threshold": 1
   },
   "2018-04-21_21:42:24.504868_2XAAS1_N": {
      "neighbors": {},
      "event_id": {},
      "cumulative_intake_sum_since_reset": 0,
      "cumulative_fire_count": 0,
      "cumulative_fire_count_inst": 0,
      "cumulative_intake_total": 0,
      "cumulative_intake_count": 0,
      "consecutive_fire_cnt": 0,
      "snooze_till_burst_num": 0,
      "last_burst_num": 0,
      "location": [
         966,
         995,
         399
      ],
      "block": [
         97,
         100,
         40
      ],
      "status": "Passive",
      "last_timer_reset_time": "2018-04-21 21:42:24.504891",
      "firing_pattern_id": "",
      "activation_function_id": "",
      "timer_threshold": 50,
      "firing_threshold": 1
   },
   "2018-04-21_21:42:24.504898_XLV1VX_N": {
      "neighbors": {},
      "event_id": {},
      "cumulative_intake_sum_since_reset": 0,
      "cumulative_fire_count": 0,
      "cumulative_fire_count_inst": 0,
      "cumulative_intake_total": 0,
      "cumulative_intake_count": 0,
      "consecutive_fire_cnt": 0,
      "snooze_till_burst_num": 0,
      "last_burst_num": 0,
      "location": [
         85,
         614,
         618
      ],
      "block": [
         9,
         62,
         62
      ],
      "status": "Passive",
      "last_timer_reset_time": "2018-04-21 21:42:24.504920",
      "firing_pattern_id": "",
      "activation_function_id": "",
      "timer_threshold": 50,
      "firing_threshold": 1
   }
}